os_refresh_config/__init__.py
os_refresh_config/os_refresh_config.py
os_refresh_config/tests/__init__.py
os_refresh_config/tests/functional/__init__.py
os_refresh_config/tests/functional/test_cmd.py
os_refresh_config/tests/unit/__init__.py
os_refresh_config/tests/unit/test_main.py
os_refresh_config/tests/unit/test_os_refresh_config.py
os_refresh_config-14.0.1.data/scripts/dib-run-parts
os_refresh_config-14.0.1.dist-info/AUTHORS
os_refresh_config-14.0.1.dist-info/LICENSE
os_refresh_config-14.0.1.dist-info/METADATA
os_refresh_config-14.0.1.dist-info/WHEEL
os_refresh_config-14.0.1.dist-info/entry_points.txt
os_refresh_config-14.0.1.dist-info/pbr.json
os_refresh_config-14.0.1.dist-info/top_level.txt
os_refresh_config-14.0.1.dist-info/RECORD
